KekikSpatula/KekikTube.py
KekikSpatula/_Kimlikler.py
KekikSpatula/_Statik.py
KekikSpatula/__init__.py
KekikSpatula/akaryakit.py
KekikSpatula/araskargo.py
KekikSpatula/bim.py
KekikSpatula/covid.py
KekikSpatula/deprem.py
KekikSpatula/discudemy.py
KekikSpatula/doviz.py
KekikSpatula/ezan.py
KekikSpatula/google.py
KekikSpatula/haber.py
KekikSpatula/havaDurumu.py
KekikSpatula/kripto.py
KekikSpatula/masal.py
KekikSpatula/n11_arama.py
KekikSpatula/nobetciEczane.py
KekikSpatula/piiz.py
KekikSpatula/sahibinden.py
KekikSpatula/trendyol_kategori.py
KekikSpatula/trendyol_urun.py
KekikSpatula/ucak.py
KekikSpatula/Lib/KekikGoogle.py
KekikSpatula/Lib/__init__.py
KekikSpatula-0.7.4.dist-info/LICENSE
KekikSpatula-0.7.4.dist-info/METADATA
KekikSpatula-0.7.4.dist-info/WHEEL
KekikSpatula-0.7.4.dist-info/top_level.txt
KekikSpatula-0.7.4.dist-info/RECORD
