Metadata-Version: 2.1
Name: KekikSpatula
Version: 0.7.4
Summary: Siz uğraşmayın diye biz uğraştık.. ~ dızz 🐍
Home-page: https://github.com/keyiflerolsun/KekikSpatula
Author: keyiflerolsun
Author-email: keyiflerolsun@gmail.com
License: GPLv3+
Keywords: KekikSpatula,KekikAkademi,keyiflerolsun
Classifier: Development Status :: 5 - Production/Stable
Classifier: License :: OSI Approved :: GNU General Public License v3 or later (GPLv3+)
Classifier: Programming Language :: Python :: 3
Requires-Python: >=3.10
License-File: LICENSE
Requires-Dist: setuptools
Requires-Dist: wheel
Requires-Dist: requests
Requires-Dist: regex
Requires-Dist: Kekik
Requires-Dist: pyTrendyol
Requires-Dist: cloudscraper
Requires-Dist: tabulate
Requires-Dist: beautifulsoup4
Requires-Dist: lxml
Requires-Dist: html5lib
Requires-Dist: pandas
Requires-Dist: pytube
Requires-Dist: pytz
Requires-Dist: parsel
Requires-Dist: pyshorteners
Requires-Dist: requests-html
